setup.py
dnsrecords/__init__.py
dnsrecords/fields.py
dnsrecords/fields_base.py
dnsrecords/records.py
dnsrecords.egg-info/PKG-INFO
dnsrecords.egg-info/SOURCES.txt
dnsrecords.egg-info/dependency_links.txt
dnsrecords.egg-info/top_level.txt