Metadata-Version: 1.0
Name: dnsrecords
Version: 0.1
Summary: Library for deal with abstract DNS records
Home-page: http://github.com/cosmin/dnsrecords
Author: Cosmin Stejerean
Author-email: cosmin@offbytwo.com
License: MIT
Platform: UNKNOWN
